django_chutney/__init__.py
django_chutney/test_utils.py
django_chutney/templatetags/__init__.py
django_chutney/templatetags/chutney_tags.py
django_chutney/tests/__init__.py
django_chutney/tests/test_test_utils.py
django_chutney-0.2.3.dist-info/licenses/LICENSE
django_chutney-0.2.3.dist-info/METADATA
django_chutney-0.2.3.dist-info/WHEEL
django_chutney-0.2.3.dist-info/top_level.txt
django_chutney-0.2.3.dist-info/RECORD
