Metadata-Version: 2.4
Name: django-chutney
Version: 0.2.3
Summary: Tasty accompaniments to go with the Django web framework.
Home-page: https://github.com/adamalton/django-chutney
Author: Adam Alton
Author-email: 270255+adamalton@users.noreply.github.com
Keywords: django
Classifier: License :: OSI Approved :: MIT License
Classifier: Framework :: Django
Classifier: Programming Language :: Python
Classifier: Programming Language :: Python :: 3
Classifier: Programming Language :: Python :: 3 :: Only
Classifier: Programming Language :: Python :: 3.8
Classifier: Programming Language :: Python :: 3.9
Classifier: Programming Language :: Python :: 3.10
Classifier: Programming Language :: Python :: 3.11
Classifier: Programming Language :: Python :: 3.12
Classifier: Programming Language :: Python :: 3.13
Requires-Python: >=3.8
License-File: LICENSE
Requires-Dist: django<6.0,>=3.2
Provides-Extra: bs4
Requires-Dist: BeautifulSoup4; extra == "bs4"
Dynamic: author
Dynamic: author-email
Dynamic: classifier
Dynamic: description
Dynamic: description-content-type
Dynamic: home-page
Dynamic: keywords
Dynamic: license-file
Dynamic: provides-extra
Dynamic: requires-dist
Dynamic: requires-python
Dynamic: summary
